fileSculpt/__init__.py
fileSculpt/filesculpt.py
filesculpt-0.0.6.dist-info/LICENSE
filesculpt-0.0.6.dist-info/METADATA
filesculpt-0.0.6.dist-info/WHEEL
filesculpt-0.0.6.dist-info/top_level.txt
filesculpt-0.0.6.dist-info/RECORD
