Metadata-Version: 2.1
Name: filesculpt
Version: 0.0.6
Summary: Abstraction of Regex find and replace on a file
Home-page: https://github.com/JuanSantosGomez/filesculpt.git
Author: Jonathan Roel Godinez
Author-email: juansantosgomez@protonmail.com
License: UNKNOWN
Platform: UNKNOWN
Classifier: Programming Language :: Python :: 3
Classifier: License :: OSI Approved :: MIT License
Classifier: Operating System :: OS Independent
Requires-Python: >=3.6
License-File: LICENSE
